pyksvd/__init__.py
pyksvd/functions.py
pyksvd/matching_pursuit.py
pyksvd/pyksvd.py
pyksvd-0.1.3.dist-info/METADATA
pyksvd-0.1.3.dist-info/WHEEL
pyksvd-0.1.3.dist-info/top_level.txt
pyksvd-0.1.3.dist-info/RECORD
