Metadata-Version: 2.1
Name: pyksvd
Version: 0.1.3
Summary: A Python implementation of the K-SVD algorithm
Home-page: https://github.com/mathias-grau/PyKSVD
Author: Mathias Grau and Antoine Martinez
Author-email: mathias4grau@gmail.com
Classifier: Programming Language :: Python :: 3
Classifier: License :: OSI Approved :: MIT License
Classifier: Operating System :: OS Independent
Requires-Python: >=3.6
